androguard/__init__.py
androguard/misc.py
androguard/session.py
androguard/util.py
androguard/core/__init__.py
androguard/core/androconf.py
androguard/core/bytecode.py
androguard/core/analysis/__init__.py
androguard/core/analysis/analysis.py
androguard/core/analysis/auto.py
androguard/core/analysis/sign.py
androguard/core/api_specific_resources/__init__.py
androguard/core/api_specific_resources/aosp_permissions/__init__.py
androguard/core/api_specific_resources/aosp_permissions/aosp_permissions.py
androguard/core/api_specific_resources/aosp_permissions/aosp_permissions_api10.py
androguard/core/api_specific_resources/aosp_permissions/aosp_permissions_api14.py
androguard/core/api_specific_resources/aosp_permissions/aosp_permissions_api15.py
androguard/core/api_specific_resources/aosp_permissions/aosp_permissions_api16.py
androguard/core/api_specific_resources/aosp_permissions/aosp_permissions_api17.py
androguard/core/api_specific_resources/aosp_permissions/aosp_permissions_api18.py
androguard/core/api_specific_resources/aosp_permissions/aosp_permissions_api19.py
androguard/core/api_specific_resources/aosp_permissions/aosp_permissions_api21.py
androguard/core/api_specific_resources/aosp_permissions/aosp_permissions_api22.py
androguard/core/api_specific_resources/aosp_permissions/aosp_permissions_api9.py
androguard/core/api_specific_resources/api_permission_mappings/__init__.py
androguard/core/api_specific_resources/api_permission_mappings/api_permission_mappings.py
androguard/core/api_specific_resources/api_permission_mappings/api_permission_mappings_api10.py
androguard/core/api_specific_resources/api_permission_mappings/api_permission_mappings_api14.py
androguard/core/api_specific_resources/api_permission_mappings/api_permission_mappings_api15.py
androguard/core/api_specific_resources/api_permission_mappings/api_permission_mappings_api16.py
androguard/core/api_specific_resources/api_permission_mappings/api_permission_mappings_api17.py
atx_androguard-3.0.dist-info/DESCRIPTION.rst
atx_androguard-3.0.dist-info/METADATA
atx_androguard-3.0.dist-info/metadata.json
atx_androguard-3.0.dist-info/RECORD
atx_androguard-3.0.dist-info/top_level.txt
atx_androguard-3.0.dist-info/WHEEL
