Metadata-Version: 2.0
Name: atx-androguard
Version: 3.0
Summary: Androguard is a full python tool to play with Android files.
Home-page: UNKNOWN
Author: UNKNOWN
Author-email: UNKNOWN
License: UNKNOWN
Platform: UNKNOWN
Requires-Dist: distribute
